{
  "kind": "collectionType",
  "collectionName": "payments",
  "info": {
    "singularName": "payment",
    "pluralName": "payments",
    "displayName": "payment",
    "description": ""
  },
  "options": {
    "draftAndPublish": false
  },
  "pluginOptions": {},
  "attributes": {
    "name": {
      "type": "string"
    },
    "thub": {
      "type": "media",
      "multiple": false,
      "required": false,
      "allowedTypes": [
        "images",
        "files",
        "videos",
        "audios"
      ]
    },
    "qr_code": {
      "type": "media",
      "multiple": false,
      "required": false,
      "allowedTypes": [
        "images",
        "files",
        "videos",
        "audios"
      ]
    },
    "state": {
      "type": "enumeration",
      "enum": [
        "active",
        "deleted"
      ]
    },
    "order": {
      "type": "integer"
    },
    "description": {
      "type": "string"
    },
    "description_en": {
      "type": "string"
    }
  }
}
